pkoffee/__init__.py
pkoffee/cli.py
pkoffee/data.py
pkoffee/fit_model.py
pkoffee/fit_model_io.py
pkoffee/log.py
pkoffee/metrics.py
pkoffee/parametric_function.py
pkoffee/productivity_analysis.py
pkoffee/visualization.py
pkoffee-0.1.0.dist-info/licenses/LICENSE
pkoffee-0.1.0.dist-info/WHEEL
pkoffee-0.1.0.dist-info/entry_points.txt
pkoffee-0.1.0.dist-info/METADATA
pkoffee-0.1.0.dist-info/RECORD
