Metadata-Version: 2.4
Name: pkoffee
Version: 0.1.0
Summary: Coffee productivity analysis with statistical modeling
Author: Thomas Vuillaume
Author-email: Thomas Vuillaume <thomas.vuillaume@lapp.in2p3.fr>
License-Expression: MIT
License-File: LICENSE
Classifier: Development Status :: 4 - Beta
Classifier: Operating System :: OS Independent
Classifier: Programming Language :: Python :: 3
Classifier: Programming Language :: Python :: 3.12
Classifier: Programming Language :: Python :: 3.13
Classifier: Intended Audience :: Science/Research
Classifier: License :: OSI Approved :: MIT License
Requires-Python: >=3.12
Project-URL: Homepage, https://github.com/s3-school/pkoffee-solution
Project-URL: Bug Tracker, https://github.com/s3-school/pkoffee-solution/issues
Project-URL: Documentation, https://github.com/s3-school/pkoffee-solution/blob/main/README.md
